[
  {
    "name": "Sơ mi phối KL",
    "priceOld": "340,000 đ",
    "price": "269,000 đ",
    "image": "https://pos.nvncdn.com/312d68-57499/ps/20240809_ZSbumNQG4j.jpeg",
    "category": "Shirt"
  },
  {
    "name": "Sơ mi tay thép kẻ phối",
    "priceOld": "450,000 đ",
    "price": "319,000 đ",
    "image": "https://pos.nvncdn.com/312d68-57499/ps/20240809_AXrUvTPXt6.jpeg",
    "category": "Shirt"
  },
  {
    "name": "Sơ mi HT L'envol",
    "priceOld": "480,000 đ",
    "price": "369,000 đ",
    "image": "https://pos.nvncdn.com/312d68-57499/ps/20240717_qlfGwBXF66.jpeg",
    "category": "Shirt"
  },
  {
    "name": "Sơ mi đính hoa Embroider",
    "priceOld": "370,000 đ",
    "price": "279,000 đ",
    "image": "https://pos.nvncdn.com/312d68-57499/ps/20240402_v5Kr4g27l0.jpeg",
    "category": "Shirt"
  },
  {
    "name": "Sơ mi Kenna",
    "priceOld": "420,000 đ",
    "price": "269,000 đ",
    "image": "https://pos.nvncdn.com/312d68-57499/ps/20240415_taAbwXKQak.jpeg",
    "category": "Shirt"
  },
  {
    "name": "Sơ mi Milya",
    "priceOld": "420,000 đ",
    "price": "199,000 đ",
    "image": "https://pos.nvncdn.com/312d68-57499/ps/20240415_jr6qC7NtPt.jpeg",
    "category": "Shirt"
  },
  {
    "name": "Sơ mi HT Down town",
    "priceOld": "399,000 đ",
    "price": "199,000 đ",
    "image": "https://pos.nvncdn.com/312d68-57499/ps/20240413_ka5z2tRccb.jpeg",
    "category": "Shirt"
  },
  {
    "name": "Sơ mi kẻ tay thép",
    "priceOld": "339,000 đ",
    "price": "199,000 đ",
    "image": "https://pos.nvncdn.com/312d68-57499/ps/20240406_0rsPEhkfqH.jpeg",
    "category": "Shirt"
  },
  {
    "name": "Sơ mi cổ victoria",
    "priceOld": "309,000 đ",
    "price": "199,000 đ",
    "image": "https://pos.nvncdn.com/312d68-57499/ps/20240403_Vr8ah3KpaT.jpeg",
    "category": "Shirt"
  },
  {
    "name": "Sơ mi lụa chìm phối trơn",
    "priceOld": "349,000 đ",
    "price": "249,000 đ",
    "image": "https://pos.nvncdn.com/312d68-57499/ps/20240404_0Euvn0hesU.jpeg",
    "category": "Shirt"
  },
  {
    "name": "Sơ mi basic dáng suông",
    "priceOld": "290,000 đ",
    "price": "199,000 đ",
    "image": "https://pos.nvncdn.com/312d68-57499/ps/20231031_jZSxSxRhw2.jpeg",
    "category": "Shirt"
  },
  {
    "name": "Sơ mi nẹp đôi",
    "priceOld": "589,000 đ",
    "price": "190,000 đ",
    "image": "https://pos.nvncdn.com/312d68-57499/ps/20240406_xaqAUYpw4P.jpeg",
    "category": "Shirt"
  },
  {
    "name": "Sơ mi túi lật",
    "priceOld": "359,000 đ",
    "price": "259,000 đ",
    "image": "https://pos.nvncdn.com/312d68-57499/ps/20240410_kE7a8gjRlU.jpeg",
    "category": "Shirt"
  }
]